<annotation>
	<folder>Chien</folder>
	<filename>2e157335d704cb4ac13b7b0b50a441e9.jpg</filename>
	<path>C:\cours_b3\mspr-ia\WildLens_MSPR\Mammiferes\Chien\2e157335d704cb4ac13b7b0b50a441e9.jpg</path>
	<source>
		<database>Unknown</database>
	</source>
	<size>
		<width>747</width>
		<height>1328</height>
		<depth>3</depth>
	</size>
	<segmented>0</segmented>
	<object>
		<name>dog</name>
		<pose>Unspecified</pose>
		<truncated>0</truncated>
		<difficult>0</difficult>
		<bndbox>
			<xmin>238</xmin>
			<ymin>570</ymin>
			<xmax>567</xmax>
			<ymax>979</ymax>
		</bndbox>
	</object>
</annotation>
