<annotation>
	<folder>Rat</folder>
	<filename>th (35).jpg</filename>
	<path>C:\cours_b3\mspr-ia\WildLens_MSPR\images_nettoyees\Rat\th (35).jpg</path>
	<source>
		<database>Unknown</database>
	</source>
	<size>
		<width>270</width>
		<height>180</height>
		<depth>3</depth>
	</size>
	<segmented>0</segmented>
	<object>
		<name>rat</name>
		<pose>Unspecified</pose>
		<truncated>0</truncated>
		<difficult>0</difficult>
		<bndbox>
			<xmin>76</xmin>
			<ymin>29</ymin>
			<xmax>118</xmax>
			<ymax>67</ymax>
		</bndbox>
	</object>
	<object>
		<name>rat</name>
		<pose>Unspecified</pose>
		<truncated>0</truncated>
		<difficult>0</difficult>
		<bndbox>
			<xmin>157</xmin>
			<ymin>33</ymin>
			<xmax>196</xmax>
			<ymax>74</ymax>
		</bndbox>
	</object>
	<object>
		<name>rat</name>
		<pose>Unspecified</pose>
		<truncated>0</truncated>
		<difficult>0</difficult>
		<bndbox>
			<xmin>128</xmin>
			<ymin>118</ymin>
			<xmax>160</xmax>
			<ymax>158</ymax>
		</bndbox>
	</object>
</annotation>