<annotation>
	<folder>Lapin</folder>
	<filename>e-up-top-down-view-shoe-footprint-right-rabbit-print-snow-close-up-171822348.jpg</filename>
	<path>C:\cours_b3\mspr-ia\WildLens_MSPR\Mammiferes\Lapin\e-up-top-down-view-shoe-footprint-right-rabbit-print-snow-close-up-171822348.jpg</path>
	<source>
		<database>Unknown</database>
	</source>
	<size>
		<width>800</width>
		<height>534</height>
		<depth>3</depth>
	</size>
	<segmented>0</segmented>
	<object>
		<name>rabbit</name>
		<pose>Unspecified</pose>
		<truncated>0</truncated>
		<difficult>0</difficult>
		<bndbox>
			<xmin>213</xmin>
			<ymin>102</ymin>
			<xmax>364</xmax>
			<ymax>422</ymax>
		</bndbox>
	</object>
</annotation>
