<annotation>
	<folder>Loup</folder>
	<filename>wolf-tracks-GKFRC3.jpg</filename>
	<path>C:\cours_b3\mspr-ia\WildLens_MSPR\images_nettoyees\Loup\wolf-tracks-GKFRC3.jpg</path>
	<source>
		<database>Unknown</database>
	</source>
	<size>
		<width>224</width>
		<height>224</height>
		<depth>3</depth>
	</size>
	<segmented>0</segmented>
	<object>
		<name>wolf</name>
		<pose>Unspecified</pose>
		<truncated>0</truncated>
		<difficult>0</difficult>
		<bndbox>
			<xmin>28</xmin>
			<ymin>111</ymin>
			<xmax>120</xmax>
			<ymax>181</ymax>
		</bndbox>
	</object>
	<object>
		<name>wolf</name>
		<pose>Unspecified</pose>
		<truncated>0</truncated>
		<difficult>0</difficult>
		<bndbox>
			<xmin>98</xmin>
			<ymin>23</ymin>
			<xmax>175</xmax>
			<ymax>87</ymax>
		</bndbox>
	</object>
</annotation>
